4.3/design.sv



 `timescale 1ns/1ns

module half_adder 
(
   input a,
   input b,
   output sum,
   output carry
);
 
 
  assign sum   = a ^ b;  // bitwise xor
  assign carry = a & b;  // bitwise and
 
endmodule // half_adder


module fulladder(s,cout,a,b,cin);
    input a,b,cin;
    output s,cout;
    assign s = a^b^cin;
    assign cout = a&&b || a&&cin || b&&cin;

endmodule

module threebit(output sum0, sum1,sum2, cout, input a0,a1,a2,b0, b1, b2);
  
  wire c1,c2;
  half_adder h(a0,b0,sum0, c1);
  fulladder f(sum1,c2,a1,b1,c1); 
  fulladder f1(sum2,cout,a2,b2,c2);
  

endmodule

// module half_adder 
// (
//    input a,
//    input b,
//    output sum,
//    output carry
// );
 
 
//   assign sum   = a ^ b;  // bitwise xor
//   assign carry = a & b;  // bitwise and
 
// endmodule // half_adder


// module fulladder(s,cout,a,b,cin);
//     input a,b,cin;
//     output s,cout;
//     assign s = a^b^cin;
//     assign cout = a&&b || a&&cin || b&&cin;

// endmodule

// // module threebit(output reg sum0, sum1,sum2, cout, input reg a0,a1,a2,b0, b1, b2);
  
// //   wire c1,c2;
// //   half_adder h(a0,b0,sum0, c1);
// //   fulladder f(sum1,c2,a1,b1,c1); 
// //   fulladder f1(sum2,cout,a2,b2,c2);
//     module threebit (  input [3:0] a,  
//                   input [3:0] b,  
//                   input c_in,  
//                   output reg c_out,  
//                   output reg [3:0] sum);  
  
//     always @ (a or b or c_in) begin  
//     {c_out, sum} = a + b + c_in;  
//   end  
// //endmodule 
  

// endmodule


// module fulladd (input [2:0] a,  
//                 input  [2:0] b,  
//                    input c_in, 
//                   output reg c_out,  
//                 output reg [2:0] sum);  
 

//   always @ (a or b or c_in) begin  
//           {c_out, sum} = a + b + c_in;  

//   end  
//endmodule

4.3/testbench.sv
`timescale 1ns/1ns

module threebittb();
   reg [2:0] a = 3'd0;
   reg [2:0] b = 3'd0;
  wire [2:0]sum;
   wire cout;
   threebit thrbit(sum[0], sum[1], sum[2], cout, a[0], a[1], a[2],b[0],b[1], b[2]);
   initial begin
      $dumpfile("dump.vcd");
      $dumpvars(1,threebittb);
     
     for (a =0; a<=2; a++)
     begin
         
       for (b =0; b<=2; b++)
         begin
           #10
           $display("a = %d, b = %d, sum = %d, cout = %d",a,b,    sum,cout);
         end 
        
     end 

      $finish;
   end
endmodule

4.3/dump.vcd
$date
	Sat Aug  6 15:45:29 2022
$end
$version
	Icarus Verilog
$end
$timescale
	1ns
$end
$scope module threebittb $end
$var wire 3 ! sum [2:0] $end
$var wire 1 " cout $end
$var reg 3 # a [2:0] $end
$var reg 3 $ b [2:0] $end
$upscope $end
$enddefinitions $end
#0
$dumpvars
b0 $
b0 #
0"
b0 !
$end
#10
b1 !
b1 $
#20
b10 !
b10 $
#30
b1 !
b1 #
b0 $
#40
b10 !
b1 $
#50
b11 !
b10 $
#60
b10 !
b10 #
b0 $
#70
b11 !
b1 $
#80
b100 !
b10 $
#90
b110 !
b11 #
b11 $
